gerk/__init__.py
gerk/_gerk_error.py
gerk/gerk.py
gerk-1.0.2.dist-info/LICENSE
gerk-1.0.2.dist-info/METADATA
gerk-1.0.2.dist-info/WHEEL
gerk-1.0.2.dist-info/top_level.txt
gerk-1.0.2.dist-info/RECORD
