Metadata-Version: 2.1
Name: gerk
Version: 1.0.2
Summary: Generalized Explicit Runge-Kutta
Author: Yasser Naji
Author-email: yfnaji@gmail.com
Keywords: runge-kutta,runge,kutta,numerical,integration,approximation
Classifier: Programming Language :: Python :: 3
Classifier: Operating System :: Unix
Classifier: Operating System :: MacOS :: MacOS X
Classifier: Operating System :: Microsoft :: Windows
License-File: LICENSE
Requires-Dist: numpy
